{
    "hostId": "TT-1M",
    "observations": [
        {
            "parameterDefinitionId": 1,
            "time": "2025-08-21T09:00:31.771499Z",
            "values": [
                {
                    "doubleValue": 12.9
                },
                {
                    "doubleValue": 33.28
                }
            ]
        },
        {
            "parameterDefinitionId": 2,
            "time": "2025-08-21T09:00:31.771605Z",
            "values": [
                {
                    "doubleValue": 2304.54
                },
                {
                    "doubleValue": 12.3
                },
                {
                    "doubleValue": 1.2
                },
                {
                    "intValue": 232
                },
                {
                    "boolValue": true
                }
            ]
        },
        {
            "parameterDefinitionId": 2,
            "time": "2025-08-21T09:00:31.771612Z",
            "values": [
                {
                    "doubleValue": 2304.54
                },
                {
                    "doubleValue": 12.3
                },
                {
                    "doubleValue": 1.2
                },
                {
                    "intValue": 232
                },
                {
                    "boolValue": true
                }
            ]
        },
        {
            "parameterDefinitionId": 2,
            "time": "2025-08-21T09:00:31.771618Z",
            "values": [
                {
                    "doubleValue": 2304.54
                },
                {
                    "doubleValue": 12.3
                },
                {
                    "doubleValue": 1.2
                },
                {
                    "intValue": 232
                },
                {
                    "boolValue": true
                }
            ]
        }
    ]
}